{
  "SettingsTitle": "设置",
  "GeneralSection": "通用",
  "HomePagePath": "主页路径",
  "DefaultSortOrder": "普通文件夹默认排序方式",
  "SortBy": "排序方式",
  "AppearanceSection": "外观",
  "MiddleFilesHeight": "中间文件列表高度",
  "AdvancedSection": "高级",
  "UseWin32Icon": "使用 Win32 API 获取图标",
  "PerformanceSection": "性能",
  "IconParallelLoading": "图标并行加载数量",
  "DebugSection": "调试",
  "UserConfigPath": "用户设置路径 *若遇到配置读写问题，请查看",
  "SaveSettings": "保存设置",
  "Language": "语言",
  "SortNameAsc": "名称升序",
  "SortNameDesc": "名称降序",
  "SortSizeDesc": "大小降序",
  "SortSizeAsc": "大小升序",
  "SortModifiedDesc": "修改时间降序",
  "SortModifiedAsc": "修改时间升序",
  "SortCreatedDesc": "创建时间降序",
  "SortCreatedAsc": "创建时间升序"
}
